mpunet/__init__.py
mpunet/augmentation/__init__.py
mpunet/augmentation/augmenters.py
mpunet/augmentation/elastic_deformation.py
mpunet/bin/__init__.py
mpunet/bin/branch.py
mpunet/bin/cv_experiment.py
mpunet/bin/cv_split.py
mpunet/bin/init_project.py
mpunet/bin/mp.py
mpunet/bin/predict.py
mpunet/bin/predict_3D.py
mpunet/bin/run_tests.py
mpunet/bin/summary.py
mpunet/bin/toy_data.py
mpunet/bin/train.py
mpunet/bin/train_fusion.py
mpunet/bin/trim_channels.py
mpunet/bin/defaults/__init__.py
mpunet/bin/defaults/3D/train_hparams.yaml
mpunet/bin/defaults/MultiPlanar/train_hparams.yaml
mpunet/bin/defaults/MultiTask/task_1.yaml
mpunet/bin/defaults/MultiTask/task_2.yaml
mpunet/bin/defaults/MultiTask/train_hparams.yaml
mpunet/bin/version/__init__.py
mpunet/bin/version/version_controller.py
mpunet/callbacks/__init__.py
mpunet/callbacks/callbacks.py
mpunet/callbacks/funcs.py
mpunet/callbacks/mcp_clean.py
mpunet/callbacks/validation.py
mpunet/database/__init__.py
mpunet/database/db_conn.py
mpunet/database/default_inserts.py
mpunet/database/default_tables.py
mpunet/errors/__init__.py
mpunet/errors/deprecated_warnings.py
mpunet/errors/image_errors.py
mpunet/errors/implementation_change_errors.py
mpunet/evaluate/__init__.py
mpunet/evaluate/loss_functions.py
mpunet/evaluate/metrics.py
mpunet/hyperparameters/__init__.py
mpunet/hyperparameters/hparams.py
mpunet/image/__init__.py
mpunet/image/auditor.py
mpunet/image/image_pair.py
mpunet/image/image_pair_loader.py
mpunet/image/image_queue.py
mpunet/image/queue/__init__.py
mpunet/image/queue/base_queue.py
mpunet/image/queue/eager_queue.py
mpunet/image/queue/lazy_queue.py
mpunet/image/queue/limitation_queue.py
mpunet/image/queue/loading_pool.py
mpunet/image/queue/utils.py
mpunet/interpolation/__init__.py
mpunet/interpolation/linalg.py
mpunet/interpolation/regular_grid_interpolator.py
mpunet/interpolation/sample_grid.py
mpunet/interpolation/view_interpolator.py
mpunet/logging/__init__.py
mpunet/logging/default_logger.py
mpunet-0.2.9.dist-info/LICENSE.txt
mpunet-0.2.9.dist-info/METADATA
mpunet-0.2.9.dist-info/WHEEL
mpunet-0.2.9.dist-info/entry_points.txt
mpunet-0.2.9.dist-info/top_level.txt
mpunet-0.2.9.dist-info/RECORD
