Metadata-Version: 2.1
Name: mpunet
Version: 0.2.9
Summary: Multi-Planar UNet for autonomous segmentation of 3D medical images
Home-page: https://github.com/perslev/MultiPlanarUNet
Author: Mathias Perslev
Author-email: map@di.ku.dk
License: LICENSE.txt
Platform: UNKNOWN
Classifier: Development Status :: 3 - Alpha
Classifier: Environment :: Console
Classifier: Operating System :: POSIX
Classifier: Programming Language :: Python :: 3
Classifier: Programming Language :: Python :: 3.5
Classifier: Programming Language :: Python :: 3.6
Classifier: Programming Language :: Python :: 3.7
Classifier: License :: OSI Approved :: MIT License
Requires-Dist: matplotlib (>=3.3.0)
Requires-Dist: scipy (>=1.4.0)
Requires-Dist: numpy (>=1.18.5)
Requires-Dist: nibabel (>=3.1.0)
Requires-Dist: pandas (>=1.0.0)
Requires-Dist: ruamel.yaml (>=0.16.0)
Requires-Dist: scikit-learn (>=0.23.0)
Requires-Dist: h5py (>=2.10.0)
Requires-Dist: psutil (>=5.7.0)
Requires-Dist: tensorflow-gpu (==2.3.2)
Requires-Dist: tensorflow-addons (==0.12.0)
